setup.py
agarnet/__init__.py
agarnet/buffer.py
agarnet/client.py
agarnet/gcommer.py
agarnet/utils.py
agarnet/vec.py
agarnet/world.py
agarnet.egg-info/PKG-INFO
agarnet.egg-info/SOURCES.txt
agarnet.egg-info/dependency_links.txt
agarnet.egg-info/pbr.json
agarnet.egg-info/requires.txt
agarnet.egg-info/top_level.txt